padding_oracle/__init__.py
padding_oracle/logger.py
padding_oracle/padding_oracle.py
padding_oracle/solve.py
padding_oracle/utils.py
padding_oracle-0.4.1.dist-info/METADATA
padding_oracle-0.4.1.dist-info/WHEEL
padding_oracle-0.4.1.dist-info/RECORD
